LICENSE
MANIFEST.in
README.rst
VERSION
setup.cfg
setup.py
nose_mocha_reporter/__init__.py
nose_mocha_reporter.egg-info/PKG-INFO
nose_mocha_reporter.egg-info/SOURCES.txt
nose_mocha_reporter.egg-info/dependency_links.txt
nose_mocha_reporter.egg-info/entry_points.txt
nose_mocha_reporter.egg-info/not-zip-safe
nose_mocha_reporter.egg-info/pbr.json
nose_mocha_reporter.egg-info/requires.txt
nose_mocha_reporter.egg-info/top_level.txt