Metadata-Version: 1.1
Name: nose-mocha-reporter
Version: 0.2
Summary: UNKNOWN
Home-page: UNKNOWN
Author: Mathieu Leplatre
Author-email: contact@mathieu-leplatre.info
License: WTFPL
Platform: UNKNOWN
Classifier: Programming Language :: Python :: 2.7
Classifier: Programming Language :: Python :: 3.4
